{
    "data": {
        "shopProductList": {
            "totalPage": 10,
            "totalProduct": 97,
            "products": [
                {
                    "id": "1003411793",
                    "productName": "10 - Rainbow - Two - way Zipper ชุดนอนเปิดเท้า",
                    "imgUrl": "https://obs.line-scdn.net:443/r/ect/ect/image_167033602299836345922de6366t10cb7507",
                    "instantDiscount": 0,
                    "price": "฿290",
                    "discountedPrice": "฿290",
                    "isInStock": true,
                    "__typename": "Product"
                },
                {
                    "id": "1003411783",
                    "productName": "09 - Rainbow - Romper",
                    "imgUrl": "https://obs.line-scdn.net:443/r/ect/ect/image_16703359256671646346c6c6530t10cb74a5",
                    "instantDiscount": 0,
                    "price": "฿360",
                    "discountedPrice": "฿360",
                    "isInStock": true,
                    "__typename": "Product"
                },
                {
                    "id": "1003411773",
                    "productName": "08 - Rainbow - Dress",
                    "imgUrl": "https://obs.line-scdn.net:443/r/ect/ect/image_1670335825371587975b5792117t10cb7441",
                    "instantDiscount": 0,
                    "price": "฿390",
                    "discountedPrice": "฿390",
                    "isInStock": true,
                    "__typename": "Product"
                },
                {
                    "id": "1003411726",
                    "productName": "07 - Rainbow - Dress",
                    "imgUrl": "https://obs.line-scdn.net:443/r/ect/ect/image_167033568464182329822dd1677t10cb73b4",
                    "instantDiscount": 0,
                    "price": "฿390",
                    "discountedPrice": "฿390",
                    "isInStock": true,
                    "__typename": "Product"
                },
                {
                    "id": "1003411547",
                    "productName": "06 - Rainbow - Sleep and Play",
                    "imgUrl": "https://obs.line-scdn.net:443/r/ect/ect/image_1670335408911127589b5781241t10cb72a0",
                    "instantDiscount": 0,
                    "price": "฿320",
                    "discountedPrice": "฿320",
                    "isInStock": true,
                    "__typename": "Product"
                },
                {
                    "id": "1003411521",
                    "productName": "05 - Rainbow - Two - way Zipper ชุดนอนคลุมเท้า",
                    "imgUrl": "https://obs.line-scdn.net:443/r/ect/ect/image_1670335272464099688b578922t10cb7218",
                    "instantDiscount": 0,
                    "price": "฿270",
                    "discountedPrice": "฿270",
                    "isInStock": true,
                    "__typename": "Product"
                },
                {
                    "id": "1003411505",
                    "productName": "04 - Rainbow - Dress",
                    "imgUrl": "https://obs.line-scdn.net:443/r/ect/ect/image_16703351510841453326c6a1132t10cb719f",
                    "instantDiscount": 0,
                    "price": "฿380",
                    "discountedPrice": "฿380",
                    "isInStock": true,
                    "__typename": "Product"
                },
                {
                    "id": "1003411491",
                    "productName": "03 - Rainbow - Romper",
                    "imgUrl": "https://obs.line-scdn.net:443/r/ect/ect/image_16703350392395710946c6c4694t10cb712f",
                    "instantDiscount": 0,
                    "price": "฿350",
                    "discountedPrice": "฿350",
                    "isInStock": true,
                    "__typename": "Product"
                },
                {
                    "id": "1003411463",
                    "productName": "02 - Rainbow - Hoodie",
                    "imgUrl": "https://obs.line-scdn.net:443/r/ect/ect/image_167033458924052838022dc7286t10cb6f6d",
                    "instantDiscount": 0,
                    "price": "฿380",
                    "discountedPrice": "฿380",
                    "isInStock": true,
                    "__typename": "Product"
                },
                {
                    "id": "1003411422",
                    "productName": "01 - Rainbow - Overall and Top",
                    "imgUrl": "https://obs.line-scdn.net:443/r/ect/ect/image_167033437502282037122df2734t10cb6e97",
                    "instantDiscount": 0,
                    "price": "฿450",
                    "discountedPrice": "฿450",
                    "isInStock": true,
                    "__typename": "Product"
                }
            ],
            "__typename": "ProductsPaging"
        }
    }
}